tapioca_harvest/__init__.py
tapioca_harvest/resource_mapping.py
tapioca_harvest/tapioca_harvest.py
tapioca_harvest-2.0.dist-info/METADATA
tapioca_harvest-2.0.dist-info/RECORD
tapioca_harvest-2.0.dist-info/WHEEL
tapioca_harvest-2.0.dist-info/top_level.txt
