Metadata-Version: 2.1
Name: tapioca-harvest
Version: 2.0
Summary: Harvest API wrapper using tapioca
Home-page: https://github.com/vintasoftware/tapioca-harvest
Author: André Ericson
Author-email: de.ericson@gmail.com
License: MIT
Keywords: harvest
Platform: UNKNOWN
Classifier: Development Status :: 5 - Production/Stable
Classifier: Intended Audience :: Developers
Classifier: License :: OSI Approved :: MIT License
Classifier: Natural Language :: English
Classifier: Programming Language :: Python :: 2
Classifier: Programming Language :: Python :: 2.7
Classifier: Programming Language :: Python :: 3
Classifier: Programming Language :: Python :: 3.1
Classifier: Programming Language :: Python :: 3.2
Classifier: Programming Language :: Python :: 3.3
Classifier: Programming Language :: Python :: 3.4
Requires-Dist: tapioca-wrapper (<0.6.0)
